lhcbdiracx/testing/__init__.py
lhcbdiracx_testing-0.0.1a3.dist-info/METADATA
lhcbdiracx_testing-0.0.1a3.dist-info/WHEEL
lhcbdiracx_testing-0.0.1a3.dist-info/top_level.txt
lhcbdiracx_testing-0.0.1a3.dist-info/RECORD
