Metadata-Version: 2.4
Name: lhcbdiracx-testing
Version: 0.0.1a3
Summary: Testing utilities for lhcbdiracx
License: GPL-3.0-only
Classifier: Intended Audience :: Science/Research
Classifier: License :: OSI Approved :: GNU General Public License v3 (GPLv3)
Classifier: Programming Language :: Python :: 3
Classifier: Topic :: Scientific/Engineering
Classifier: Topic :: System :: Distributed Computing
Requires-Python: >=3.11
Requires-Dist: diracx-testing
